{
  "settings" : {
    "analysis" : {
      "analyzer" : {
        "pinyin_analyzer" : {
          "tokenizer" : "my_pinyin",
          "filter" : "word_delimiter"
        },
        "optimizeIK":{
          "type":"custom",
          "tokenizer":"ik_max_word",
          "filter":["stemmer","word_delimiter","lowercase"]
        }
      },
      "tokenizer" : {
        "my_pinyin" : {
          "type" : "pinyin",
          "first_letter" : "none",
          "padding_char" : " "
        }
      }
    }
  },
  "mappings": {
    "_default_":{
      "_all":{
        "enabled":false
      }
    },

    "aus_at_picture_list":{
      "dynamic":"false",
      "properties": {
        "PICTURE_ID":{
          "type": "string",
          "index": "not_analyzed"
        },
        "BILL_NO":{
          "type": "string",
          "index": "not_analyzed"
        },
        "BILL_TYPE":{
          "type": "string",
          "index": "not_analyzed"
        },
        "PIC_NAME":{
          "type": "string",
          "index": "not_analyzed"
        },
        "PIC_TYPE":{
          "type": "string",
          "index": "not_analyzed"
        },
        "FILE_PATH":{
          "type": "string",
          "index": "not_analyzed"
        },
        "PIC_SIZE":{
          "type": "double",
          "index": "not_analyzed"
        },
        "PIC_STORAGE_NAME":{
          "type": "string",
          "index": "not_analyzed"
        },
        "PIC_EX_FILEID":{
          "type": "string",
          "index": "not_analyzed"
        },
        "SMALL_SIZE_NAME":{
          "type": "string",
          "index": "not_analyzed"
        },
        "SMALL_SIZE_EX_FILE_ID":{
          "type": "string",
          "index": "not_analyzed"
        },
        "MIDDLE_SIZE_NAME":{
          "type": "string",
          "index": "not_analyzed"
        },
        "MIDDLE_SIZE_EX_FILE_ID":{
          "type": "string",
          "index": "not_analyzed"
        },
        "PIC_STATUS":{
          "type": "string",
          "index": "not_analyzed"
        },
        "CREATE_USER_ID":{
          "type":"string",
          "index":"not_analyzed"
        },
        "CREATE_DATE":{
          "type": "date",
          "format": "yyyy-MM-dd HH:mm:ss||yyyy-MM-dd||epoch_millis"
        },
        "CREATE_USER_NAME":{
          "type":"string",
          "index":"not_analyzed"
        },

        "MODIFY_USER_ID":{
          "type":"string",
          "index":"not_analyzed"
        },
        "MODIFY_DATE":{
          "type": "date",
          "format": "yyyy-MM-dd HH:mm:ss||yyyy-MM-dd||epoch_millis"
        },
        "MODIFY_USER_NAME":{
          "type":"string",
          "index":"not_analyzed"
        },
        "ORG_ID":{
          "type":"string",
          "index":"not_analyzed"
        },
        "BOOK_ID":{
          "type":"string",
          "index":"not_analyzed"
        },
        "GROUP_ID":{
          "type":"string",
          "index":"not_analyzed"
        },
        "EXT_COL1":{
          "type":"string",
          "index":"not_analyzed"
        },
        "EXT_COL2":{
          "type":"string",
          "index":"not_analyzed"
        },
        "EXT_COL3":{
          "type":"string",
          "index":"not_analyzed"
        },
        "EXT_COL4":{
          "type":"string",
          "index":"not_analyzed"
        },
        "EXT_COL5":{
          "type":"string",
          "index":"not_analyzed"
        },
        "EXT_COL6":{
          "type":"string",
          "index":"not_analyzed"
        },
        "EXT_COL7":{
          "type":"string",
          "index":"not_analyzed"
        },
        "EXT_COL8":{
          "type":"string",
          "index":"not_analyzed"
        },
        "EXT_COL9":{
          "type":"string",
          "index":"not_analyzed"
        },
        "EXT_COL10":{
          "type":"string",
          "index":"not_analyzed"
        }
      }
    },
    "spu":{
      "dynamic":"false",
      "properties": {
        "SPU_ID":{
          "type": "string",
          "index": "not_analyzed"
        },
        "CATEGORY_ID":{
          "type": "string",
          "index": "not_analyzed"
        },
        "SPEC_HEAD_ID":{
          "type": "string",
          "index": "not_analyzed"
        },
        "SPU_CODE":{
          "type": "string",
          "index": "not_analyzed"
        },
        "SPU_NAME": {
          "type": "multi_field",
          "fields": {
            "pinyin": {
              "type": "string",
              "store": "no",
              "term_vector": "with_positions_offsets",
              "analyzer": "pinyin_analyzer",
              "boost": 10
            },
            "SPU_NAME": {
              "type": "string",
              "term_vector": "with_positions_offsets",
              "index": "analyzed",
              "analyzer": "optimizeIK",
              "search_analyzer": "optimizeIK",
              "include_in_all": "true"
            }
          }
        },
        "SPU_STATUS":{
          "type": "string",
          "index": "not_analyzed"
        },
        "SPU_TYPE":{
          "type": "string",
          "index": "not_analyzed"
        },
        "SPU_DESC":{
          "type": "string",
          "term_vector": "with_positions_offsets",
          "index": "analyzed",
          "analyzer": "optimizeIK",
          "search_analyzer": "optimizeIK",
          "include_in_all": "true"
        },
        "BRAND":{
          "type": "string",
          "index": "not_analyzed"
        },
        "PRIMARY_UNIT_CODE":{
          "type": "string",
          "index": "not_analyzed"
        },
        "TAX_RATE":{
          "type": "string",
          "index": "not_analyzed"
        },
        "SPEC_VALUE1": {
          "type": "string",
          "index": "not_analyzed"
        },
        "SPEC_VALUE2": {
          "type": "string",
          "index": "not_analyzed"
        },
        "SPEC_VALUE3": {
          "type": "string",
          "index": "not_analyzed"
        },
        "SPEC_VALUE4": {
          "type": "string",
          "index": "not_analyzed"
        },
        "SPEC_VALUE5": {
          "type": "string",
          "index": "not_analyzed"
        },
        "SPEC_VALUE6": {
          "type": "string",
          "index": "not_analyzed"
        },
        "SPEC_VALUE7": {
          "type": "string",
          "index": "not_analyzed"
        },
        "SPEC_VALUE8": {
          "type": "string",
          "index": "not_analyzed"
        },
        "SPEC_VALUE9": {
          "type": "string",
          "index": "not_analyzed"
        },
        "SPEC_VALUE10": {
          "type": "string",
          "index": "not_analyzed"
        },
        "SPEC_VALUE11": {
          "type": "string",
          "index": "not_analyzed"
        },
        "SPEC_VALUE12": {
          "type": "string",
          "index": "not_analyzed"
        },
        "SPEC_VALUE13": {
          "type": "string",
          "index": "not_analyzed"
        },
        "SPEC_VALUE14": {
          "type": "string",
          "index": "not_analyzed"
        },
        "SPEC_VALUE15": {
          "type": "string",
          "index": "not_analyzed"
        },
        "SPEC_VALUE16": {
          "type": "string",
          "index": "not_analyzed"
        },
        "SPEC_VALUE17": {
          "type": "string",
          "index": "not_analyzed"
        },
        "SPEC_VALUE18": {
          "type": "string",
          "index": "not_analyzed"
        },
        "SPEC_VALUE19": {
          "type": "string",
          "index": "not_analyzed"
        },
        "SPEC_VALUE20": {
          "type": "string",
          "index": "not_analyzed"
        },
        "CREATE_USER_ID":{
          "type":"string",
          "index":"not_analyzed"
        },
        "CREATE_DATE":{
          "type": "date",
          "format": "yyyy-MM-dd HH:mm:ss||yyyy-MM-dd||epoch_millis"
        },
        "CREATE_USER_NAME":{
          "type":"string",
          "index":"not_analyzed"
        },

        "MODIFY_USER_ID":{
          "type":"string",
          "index":"not_analyzed"
        },
        "MODIFY_DATE":{
          "type": "date",
          "format": "yyyy-MM-dd HH:mm:ss||yyyy-MM-dd||epoch_millis"
        },
        "MODIFY_USER_NAME":{
          "type":"string",
          "index":"not_analyzed"
        },
        "ORG_ID":{
          "type":"string",
          "index":"not_analyzed"
        },
        "BOOK_ID":{
          "type":"string",
          "index":"not_analyzed"
        },
        "GROUP_ID":{
          "type":"string",
          "index":"not_analyzed"
        },
        "EXT_COL1":{
          "type":"string",
          "index":"not_analyzed"
        },
        "EXT_COL2":{
          "type":"string",
          "index":"not_analyzed"
        },
        "EXT_COL3":{
          "type":"string",
          "index":"not_analyzed"
        },
        "EXT_COL4":{
          "type":"string",
          "index":"not_analyzed"
        },
        "EXT_COL5":{
          "type":"string",
          "index":"not_analyzed"
        },
        "EXT_COL6":{
          "type":"string",
          "index":"not_analyzed"
        },
        "EXT_COL7":{
          "type":"string",
          "index":"not_analyzed"
        },
        "EXT_COL8":{
          "type":"string",
          "index":"not_analyzed"
        },
        "EXT_COL9":{
          "type":"string",
          "index":"not_analyzed"
        },
        "EXT_COL10":{
          "type":"string",
          "index":"not_analyzed"
        },
        "TAX_CODE_TYPE":{
          "type":"string",
          "index":"not_analyzed"
        },
        "SPU_DETAIL_NOTES":{
          "type": "string",
          "term_vector": "with_positions_offsets",
          "index": "analyzed",
          "analyzer": "optimizeIK",
          "search_analyzer": "optimizeIK",
          "include_in_all": "true"
        }
      }
    },
    "item_price":{
      "dynamic":"false",
      "properties": {
        "ITEM_PRICE_ID":{
          "type": "string",
          "index": "not_analyzed"
        },
        "ITEM_LINE_ID":{
          "type": "string",
          "index": "not_analyzed"
        },
        "PRICE_TYPE":{
          "type": "string",
          "index": "not_analyzed"
        },
        "PUR_PRICE1":{
          "type": "double",
          "index": "not_analyzed"
        },
        "PUR_PRICE2":{
          "type": "double",
          "index": "not_analyzed"
        },
        "PUR_PRICE3":{
          "type": "double",
          "index": "not_analyzed"
        },
        "PUR_PRICE4": {
          "type": "double",
          "index": "not_analyzed"
        }, "PUR_PRICE5":{
          "type": "double",
          "index": "not_analyzed"
        },
        "SALE_PRICE1":{
          "type": "double",
          "index": "not_analyzed"
        },
        "SALE_PRICE2":{
          "type": "double",
          "index": "not_analyzed"
        },
        "SALE_PRICE3":{
          "type": "double",
          "index": "not_analyzed"
        },
        "SALE_PRICE4":{
          "type": "double",
          "index": "not_analyzed"
        },
        "SALE_PRICE5":{
          "type": "double",
          "index": "not_analyzed"
        },
        "VALID_DATE":{
          "type": "date",
          "format": "yyyy-MM-dd HH:mm:ss||yyyy-MM-dd||epoch_millis"
        },
        "INVALID_DATE":{
          "type": "date",
          "format": "yyyy-MM-dd HH:mm:ss||yyyy-MM-dd||epoch_millis"
        },
        "CREATE_USER_ID":{
          "type":"string",
          "index":"not_analyzed"
        },
        "CREATE_DATE":{
          "type": "date",
          "format": "yyyy-MM-dd HH:mm:ss||yyyy-MM-dd||epoch_millis"
        },
        "CREATE_USER_NAME":{
          "type":"string",
          "index":"not_analyzed"
        },

        "MODIFY_USER_ID":{
          "type":"string",
          "index":"not_analyzed"
        },
        "MODIFY_DATE":{
          "type": "date",
          "format": "yyyy-MM-dd HH:mm:ss||yyyy-MM-dd||epoch_millis"
        },
        "MODIFY_USER_NAME":{
          "type":"string",
          "index":"not_analyzed"
        },
        "ORG_ID":{
          "type":"string",
          "index":"not_analyzed"
        },
        "BOOK_ID":{
          "type":"string",
          "index":"not_analyzed"
        },
        "GROUP_ID":{
          "type":"string",
          "index":"not_analyzed"
        },
        "EXT_COL1":{
          "type":"string",
          "index":"not_analyzed"
        },
        "EXT_COL2":{
          "type":"string",
          "index":"not_analyzed"
        },
        "EXT_COL3":{
          "type":"string",
          "index":"not_analyzed"
        },
        "EXT_COL4":{
          "type":"string",
          "index":"not_analyzed"
        },
        "EXT_COL5":{
          "type":"string",
          "index":"not_analyzed"
        },
        "EXT_COL6":{
          "type":"string",
          "index":"not_analyzed"
        },
        "EXT_COL7":{
          "type":"string",
          "index":"not_analyzed"
        },
        "EXT_COL8":{
          "type":"string",
          "index":"not_analyzed"
        },
        "EXT_COL9":{
          "type":"string",
          "index":"not_analyzed"
        },
        "EXT_COL10":{
          "type":"string",
          "index":"not_analyzed"
        }
      }
    },
    "item_line":{
      "dynamic":"false",
      "properties": {
        "ITEM_LINE_ID":{
          "type": "string",
          "index": "not_analyzed"
        },
        "ITEM_ID":{
          "type": "string",
          "index": "not_analyzed"
        },
        "ITEM_LINE_CODE":{
          "type": "string",
          "index": "not_analyzed"
        },
        "MATERIAL_TYPE_CODE":{
          "type": "string",
          "index": "not_analyzed"
        },
        "SUPPLIER_ID":{
          "type": "string",
          "index": "not_analyzed"
        },
        "TAX_CODE_TYPE":{
          "type": "string",
          "index": "not_analyzed"
        },
        "TAX_CODE":{
          "type": "string",
          "index": "not_analyzed"
        },
        "MIN_ORDER_NUM":{
          "type": "double",
          "index": "not_analyzed"
        },
        "PACKAGE_NUM":{
          "type": "double",
          "index": "not_analyzed"
        },
        "LEAD_TIME":{
          "type": "double",
          "index": "not_analyzed"
        },
        "ITEM_VALID_DATE":{
          "type": "date",
          "format": "yyyy-MM-dd HH:mm:ss||yyyy-MM-dd||epoch_millis"
        },
        "ITEM_INVALID_DATE":{
          "type": "date",
          "format": "yyyy-MM-dd HH:mm:ss||yyyy-MM-dd||epoch_millis"
        },
        "MATERIAL_ACCOUNT":{
          "type": "string",
          "index": "not_analyzed"
        },
        "DOWN_PRICE_ACCOUNT":{
          "type": "string",
          "index": "not_analyzed"
        },
        "COST_ACCOUNT":{
          "type": "string",
          "index": "not_analyzed"
        },
        "REVENUE_ACCOUNT":{
          "type": "string",
          "index": "not_analyzed"
        },
        "RECEIVE_ACCOUNT":{
          "type": "string",
          "index": "not_analyzed"
        },
        "REVE_ADV_ACCOUNT":{
          "type": "string",
          "index": "not_analyzed"
        },
        "PAY_ACCOUNT":{
          "type": "string",
          "index": "not_analyzed"
        },
        "PREPAY_ACCOUNT":{
          "type": "string",
          "index": "not_analyzed"
        },
        "EXPENSE_ACCOUNT":{
          "type": "string",
          "index": "not_analyzed"
        },
        "GTP_COST_ACCOUNT":{
          "type": "string",
          "index": "not_analyzed"
        },
        "GTP_REVENUE_ACCOUNT":{
          "type": "string",
          "index": "not_analyzed"
        },
        "MATCH_FLAG":{
          "type": "string",
          "index": "not_analyzed"
        },
        "EFFECT_USER_ID":{
          "type": "string",
          "index": "not_analyzed"
        },
        "EFFECT_DATE":{
          "type": "date",
          "format": "yyyy-MM-dd HH:mm:ss||yyyy-MM-dd||epoch_millis"
        },
        "INVALID_USER_ID":{
          "type": "string",
          "index": "not_analyzed"
        },
        "INVALID_DATE":{
          "type": "date",
          "format": "yyyy-MM-dd HH:mm:ss||yyyy-MM-dd||epoch_millis"
        },
        "DISPLAY_FLAG":{
          "type": "string",
          "index": "not_analyzed"
        },
        "STATUS":{
          "type": "string",
          "index": "not_analyzed"
        },
        "CREATE_USER_ID":{
          "type":"string",
          "index":"not_analyzed"
        },
        "CREATE_DATE":{
          "type": "date",
          "format": "yyyy-MM-dd HH:mm:ss||yyyy-MM-dd||epoch_millis"
        },
        "CREATE_USER_NAME":{
          "type":"string",
          "index":"not_analyzed"
        },

        "MODIFY_USER_ID":{
          "type":"string",
          "index":"not_analyzed"
        },
        "MODIFY_DATE":{
          "type": "date",
          "format": "yyyy-MM-dd HH:mm:ss||yyyy-MM-dd||epoch_millis"
        },
        "MODIFY_USER_NAME":{
          "type":"string",
          "index":"not_analyzed"
        },
        "ORG_ID":{
          "type":"string",
          "index":"not_analyzed"
        },
        "BOOK_ID":{
          "type":"string",
          "index":"not_analyzed"
        },
        "GROUP_ID":{
          "type":"string",
          "index":"not_analyzed"
        },
        "EXT_COL1":{
          "type":"string",
          "index":"not_analyzed"
        },
        "EXT_COL2":{
          "type":"string",
          "index":"not_analyzed"
        },
        "EXT_COL3":{
          "type":"string",
          "index":"not_analyzed"
        },
        "EXT_COL4":{
          "type":"string",
          "index":"not_analyzed"
        },
        "EXT_COL5":{
          "type":"string",
          "index":"not_analyzed"
        },
        "EXT_COL6":{
          "type":"string",
          "index":"not_analyzed"
        },
        "EXT_COL7":{
          "type":"string",
          "index":"not_analyzed"
        },
        "EXT_COL8":{
          "type":"string",
          "index":"not_analyzed"
        },
        "EXT_COL9":{
          "type":"string",
          "index":"not_analyzed"
        },
        "EXT_COL10":{
          "type":"string",
          "index":"not_analyzed"
        },
        "AREA_NAME":{
          "type":"string",
          "index":"not_analyzed"
        },
        "AREA_CODE":{
          "type":"string",
          "index":"not_analyzed"
        },
        "SUPPLIER_CODE":{
          "type":"string",
          "index":"not_analyzed"
        },
        "SUPPLIER_NAME":{
          "type":"string",
          "index":"not_analyzed"
        },
        "ITEM_LINE_OUTSYS_CODE":{
          "type":"string",
          "index":"not_analyzed"
        }
      }
    },
    "item":{
      "dynamic":"false",
      "properties": {
        "ITEM_ID": {
          "type": "string",
          "index": "not_analyzed"
        },
        "CATEGORY_ID": {
          "type": "string",
          "index": "not_analyzed"
        },
        "SPU_ID": {
          "type": "string",
          "index": "not_analyzed"
        },
        "ITEM_TYPE": {
          "type": "string",
          "index": "not_analyzed"
        },
        "SPEC_HEAD_ID": {
          "type": "string",
          "index": "not_analyzed"
        },
        "ITEM_CODE": {
          "type": "string",
          "index": "not_analyzed"
        },
        "ITEM_NAME": {
          "type": "multi_field",
          "fields": {
            "pinyin": {
              "type": "string",
              "store": "no",
              "term_vector": "with_positions_offsets",
              "analyzer": "pinyin_analyzer",
              "boost": 10
            },
            "ITEM_NAME": {
              "type": "string",
              "term_vector": "with_positions_offsets",
              "index": "analyzed",
              "analyzer": "optimizeIK",
              "search_analyzer": "optimizeIK",
              "include_in_all": "true"
            }
          }
        },
        "ITEM_SHORTNAME": {
          "type": "multi_field",
          "fields": {
            "pinyin": {
              "type": "string",
              "store": "no",
              "term_vector": "with_positions_offsets",
              "analyzer": "pinyin_analyzer",
              "boost": 10
            },
            "ITEM_SHORTNAME": {
              "type": "string",
              "term_vector": "with_positions_offsets",
              "index": "analyzed",
              "analyzer": "optimizeIK",
              "search_analyzer": "optimizeIK",
              "include_in_all": "true"
            }
          }
        },
        "ITEM_STATUS": {
          "type": "string",
          "index": "not_analyzed"
        },
        "ITEM_DESC": {
          "type": "string",
          "term_vector": "with_positions_offsets",
          "index": "analyzed",
          "analyzer": "optimizeIK",
          "search_analyzer": "optimizeIK",
          "include_in_all": "true"
        },
        "TRADEMARK": {
          "type": "string",
          "index": "not_analyzed"
        },
        "PRIMARY_UNIT_CODE":{
          "type": "string",
          "index": "not_analyzed"
        },
        "VALID_START":{
          "type": "date",
          "format": "yyyy-MM-dd HH:mm:ss||yyyy-MM-dd||epoch_millis"
        },
        "VALID_END":{
          "type": "date",
          "format": "yyyy-MM-dd HH:mm:ss||yyyy-MM-dd||epoch_millis"
        },
        "EFFECT_USER_ID":{
          "type": "string",
          "index": "not_analyzed"
        },
        "EFFECT_DATE":{
          "type": "date",
          "format": "yyyy-MM-dd HH:mm:ss||yyyy-MM-dd||epoch_millis"
        },
        "INVALID_USER_ID":{
          "type": "string",
          "index": "not_analyzed"
        },
        "INVALID_DATE":{
          "type": "date",
          "format": "yyyy-MM-dd HH:mm:ss||yyyy-MM-dd||epoch_millis"
        },
        "SECONDARY_UNIT_CODE":{
          "type": "string",
          "index": "not_analyzed"
        },
        "PO_MOREORLESS_UP":{
          "type":"double",
          "index": "not_analyzed"
        },
        "PO_MOREORLESS_DOWN":{
          "type":"double",
          "index": "not_analyzed"
        },
        "ONT_MOREORLESS_UP":{
          "type":"double",
          "index": "not_analyzed"
        },
        "ONT_MOREORLESS_DOWN":{
          "type":"double",
          "index": "not_analyzed"
        },
        "UOM_WIDTH":{
          "type": "string",
          "index": "not_analyzed"
        },
        "UOM_HEIGHT":{
          "type": "string",
          "index": "not_analyzed"
        },
        "UOM_LENGTH":{
          "type": "string",
          "index": "not_analyzed"
        },
        "UOM_DENSITY":{
          "type": "string",
          "index": "not_analyzed"
        },
        "UOM_WEIGHT":{
          "type": "string",
          "index": "not_analyzed"
        },
        "HS_CODE":{
          "type": "string",
          "index": "not_analyzed"
        },
        "MARK_CODE":{
          "type": "string",
          "index": "not_analyzed"
        },
        "MANUFACTURER_NAME":{
          "type": "string",
          "index": "not_analyzed"
        },
        "TECHNICAL_STANDARD":{
          "type": "string",
          "index": "not_analyzed"
        },
        "GOLDEN_TAX_CODE":{
          "type": "string",
          "index": "not_analyzed"
        },
        "LOSS_RATE":{
          "type": "double",
          "index": "not_analyzed"
        },
        "STANDARD_FLAG":{
          "type": "string",
          "index": "not_analyzed"
        },
        "ORIGIN":{
          "type": "string",
          "index": "not_analyzed"
        },
        "LOCK_FLAG":{
          "type": "string",
          "index": "not_analyzed"
        },
        "SPEC_VALUE1": {
          "type": "string",
          "index": "not_analyzed"
        },
        "SPEC_VALUE2": {
          "type": "string",
          "index": "not_analyzed"
        },
        "SPEC_VALUE3": {
          "type": "string",
          "index": "not_analyzed"
        },
        "SPEC_VALUE4": {
          "type": "string",
          "index": "not_analyzed"
        },
        "SPEC_VALUE5": {
          "type": "string",
          "index": "not_analyzed"
        },
        "SPEC_VALUE6": {
          "type": "string",
          "index": "not_analyzed"
        },
        "SPEC_VALUE7": {
          "type": "string",
          "index": "not_analyzed"
        },
        "SPEC_VALUE8": {
          "type": "string",
          "index": "not_analyzed"
        },
        "SPEC_VALUE9": {
          "type": "string",
          "index": "not_analyzed"
        },
        "SPEC_VALUE10": {
          "type": "string",
          "index": "not_analyzed"
        },
        "SPEC_VALUE11": {
          "type": "string",
          "index": "not_analyzed"
        },
        "SPEC_VALUE12": {
          "type": "string",
          "index": "not_analyzed"
        },
        "SPEC_VALUE13": {
          "type": "string",
          "index": "not_analyzed"
        },
        "SPEC_VALUE14": {
          "type": "string",
          "index": "not_analyzed"
        },
        "SPEC_VALUE15": {
          "type": "string",
          "index": "not_analyzed"
        },
        "SPEC_VALUE16": {
          "type": "string",
          "index": "not_analyzed"
        },
        "SPEC_VALUE17": {
          "type": "string",
          "index": "not_analyzed"
        },
        "SPEC_VALUE18": {
          "type": "string",
          "index": "not_analyzed"
        },
        "SPEC_VALUE19": {
          "type": "string",
          "index": "not_analyzed"
        },
        "SPEC_VALUE20": {
          "type": "string",
          "index": "not_analyzed"
        },
        "CREATE_USER_ID":{
          "type":"string",
          "index":"not_analyzed"
        },
        "CREATE_DATE":{
          "type": "date",
          "format": "yyyy-MM-dd HH:mm:ss||yyyy-MM-dd||epoch_millis"
        },
        "CREATE_USER_NAME":{
          "type":"string",
          "index":"not_analyzed"
        },

        "MODIFY_USER_ID":{
          "type":"string",
          "index":"not_analyzed"
        },
        "MODIFY_DATE":{
          "type": "date",
          "format": "yyyy-MM-dd HH:mm:ss||yyyy-MM-dd||epoch_millis"
        },
        "MODIFY_USER_NAME":{
          "type":"string",
          "index":"not_analyzed"
        },
        "ORG_ID":{
          "type":"string",
          "index":"not_analyzed"
        },
        "BOOK_ID":{
          "type":"string",
          "index":"not_analyzed"
        },
        "GROUP_ID":{
          "type":"string",
          "index":"not_analyzed"
        },
        "EXT_COL1":{
          "type":"string",
          "index":"not_analyzed"
        },
        "EXT_COL2":{
          "type":"string",
          "index":"not_analyzed"
        },
        "EXT_COL3":{
          "type":"string",
          "index":"not_analyzed"
        },
        "EXT_COL4":{
          "type":"string",
          "index":"not_analyzed"
        },
        "EXT_COL5":{
          "type":"string",
          "index":"not_analyzed"
        },
        "EXT_COL6":{
          "type":"string",
          "index":"not_analyzed"
        },
        "EXT_COL7":{
          "type":"string",
          "index":"not_analyzed"
        },
        "EXT_COL8":{
          "type":"string",
          "index":"not_analyzed"
        },
        "EXT_COL9":{
          "type":"string",
          "index":"not_analyzed"
        },
        "EXT_COL10":{
          "type":"string",
          "index":"not_analyzed"
        },

        "FROM_TYPE":{
          "type":"string",
          "index":"not_analyzed"
        },
        "FROM_ID":{
          "type":"string",
          "index":"not_analyzed"
        },
        "TAX_CODE_TYPE":{
          "type":"string",
          "index":"not_analyzed"
        },
        "TAX_RATE":{
          "type":"string",
          "index":"not_analyzed"
        },
        "ITEM_DETAIL_NOTES":{
          "type": "string",
          "term_vector": "with_positions_offsets",
          "index": "analyzed",
          "analyzer": "optimizeIK",
          "search_analyzer": "optimizeIK",
          "include_in_all": "true"
        }
      }
    },
    "brand":{
      "dynamic":"false",
      "properties":{
        "BRAND_ID":{
          "type":"string",
          "index":"not_analyzed"
        },
        "BRAND_NAME":{
          "type": "string",
          "term_vector": "with_positions_offsets",
          "index": "analyzed",
          "analyzer": "optimizeIK",
          "search_analyzer": "optimizeIK",
          "include_in_all": "true"
        },
        "STATUS":{
          "type":"string",
          "index":"not_analyzed"
        },
        "BRIEF_NAME":{
          "type": "string",
          "term_vector": "with_positions_offsets",
          "index": "analyzed",
          "analyzer": "optimizeIK",
          "search_analyzer": "optimizeIK",
          "include_in_all": "true"
        },
        "WEBSITE":{
          "type":"string",
          "index":"not_analyzed"
        },
        "CATEGORY_ID":{
          "type":"string",
          "index":"not_analyzed"
        },
        "LOGO_URL":{
          "type":"string",
          "index":"not_analyzed"
        },
        "BRAND_STORY_TITLE":{
          "type": "string",
          "term_vector": "with_positions_offsets",
          "index": "analyzed",
          "analyzer": "optimizeIK",
          "search_analyzer": "optimizeIK",
          "include_in_all": "true"
        },
        "BELONG_COUNTRY":{
          "type":"string",
          "index":"not_analyzed"
        },
        "BELONG_COMPANY":{
          "type":"string",
          "index":"not_analyzed"
        },
        "FOUND_YEAR":{
          "type":"string",
          "index":"not_analyzed"
        },
        "CREATE_USER_ID":{
          "type":"string",
          "index":"not_analyzed"
        },
        "CREATE_DATE":{
          "type": "date",
          "format": "yyyy-MM-dd HH:mm:ss||yyyy-MM-dd||epoch_millis"
        },
        "CREATE_USER_NAME":{
          "type":"string",
          "index":"not_analyzed"
        },

        "MODIFY_USER_ID":{
          "type":"string",
          "index":"not_analyzed"
        },
        "MODIFY_DATE":{
          "type": "date",
          "format": "yyyy-MM-dd HH:mm:ss||yyyy-MM-dd||epoch_millis"
        },
        "MODIFY_USER_NAME":{
          "type":"string",
          "index":"not_analyzed"
        },
        "ORG_ID":{
          "type":"string",
          "index":"not_analyzed"
        },
        "BOOK_ID":{
          "type":"string",
          "index":"not_analyzed"
        },
        "GROUP_ID":{
          "type":"string",
          "index":"not_analyzed"
        },
        "EXT_COL1":{
          "type":"string",
          "index":"not_analyzed"
        },
        "EXT_COL2":{
          "type":"string",
          "index":"not_analyzed"
        },
        "EXT_COL3":{
          "type":"string",
          "index":"not_analyzed"
        },
        "EXT_COL4":{
          "type":"string",
          "index":"not_analyzed"
        },
        "EXT_COL5":{
          "type":"string",
          "index":"not_analyzed"
        },
        "EXT_COL6":{
          "type":"string",
          "index":"not_analyzed"
        },
        "EXT_COL7":{
          "type":"string",
          "index":"not_analyzed"
        },
        "EXT_COL8":{
          "type":"string",
          "index":"not_analyzed"
        },
        "EXT_COL9":{
          "type":"string",
          "index":"not_analyzed"
        },
        "EXT_COL10":{
          "type":"string",
          "index":"not_analyzed"
        },
        "BRAND_INTRODUCTION_NOTES":{
          "type": "string",
          "term_vector": "with_positions_offsets",
          "index": "analyzed",
          "analyzer": "optimizeIK",
          "search_analyzer": "optimizeIK",
          "include_in_all": "true"
        },
        "BRAND_STORY_NOTES":{
          "type": "string",
          "term_vector": "with_positions_offsets",
          "index": "analyzed",
          "analyzer": "optimizeIK",
          "search_analyzer": "optimizeIK",
          "include_in_all": "true"
        }
      }
    },
    "category":{
      "dynamic":"false",
      "properties": {
        "CATEGORY_ID": {
          "type": "string",
          "index": "not_analyzed"
        },
        "CATEGORY_CODE":{
          "type": "string",
          "index": "not_analyzed"
        },
        "CATEGORY_NAME":{
          "type": "string",
          "index": "not_analyzed"
        },
        "CATEGORY_DESC":{
          "type": "string",
          "index": "not_analyzed"
        },
        "PARENT_CATEGORY_ID":{
          "type": "string",
          "index": "not_analyzed"
        },
        "CATEGORY_FULL_CODE":{
          "type": "string",
          "index": "not_analyzed"
        },
        "CATEGORY_FULL_NAME":{
          "type": "string",
          "index": "not_analyzed"
        },
        "CATEGORY_LEVEL":{
          "type": "string",
          "index": "not_analyzed"
        },
        "CATEGORY_SORT":{
          "type":"double",
          "index": "not_analyzed"
        },
        "STATUS":{
          "type": "string",
          "index": "not_analyzed"
        },
        "CATEGORY_MANAGER":{
          "type": "string",
          "index": "not_analyzed"
        },
        "EFFECT_USER_ID":{
          "type":"string",
          "index": "not_analyzed"
        },
        "EFFECT_DATE":{
          "type": "date",
          "format": "yyyy-MM-dd HH:mm:ss||yyyy-MM-dd||epoch_millis"
        },
        "INVALID_USER_ID":{
          "type": "string",
          "index": "not_analyzed"
        },
        "INVALID_DATE":{
          "type": "date",
          "format": "yyyy-MM-dd HH:mm:ss||yyyy-MM-dd||epoch_millis"
        },
        "SPEC_DEFINE_ID":{
          "type": "string",
          "index": "not_analyzed"
        },
        "CREATE_USER_ID":{
          "type":"string",
          "index":"not_analyzed"
        },
        "CREATE_DATE":{
          "type": "date",
          "format": "yyyy-MM-dd HH:mm:ss||yyyy-MM-dd||epoch_millis"
        },
        "CREATE_USER_NAME":{
          "type":"string",
          "index":"not_analyzed"
        },

        "MODIFY_USER_ID":{
          "type":"string",
          "index":"not_analyzed"
        },
        "MODIFY_DATE":{
          "type": "date",
          "format": "yyyy-MM-dd HH:mm:ss||yyyy-MM-dd||epoch_millis"
        },
        "MODIFY_USER_NAME":{
          "type":"string",
          "index":"not_analyzed"
        },
        "ORG_ID":{
          "type":"string",
          "index":"not_analyzed"
        },
        "BOOK_ID":{
          "type":"string",
          "index":"not_analyzed"
        },
        "GROUP_ID":{
          "type":"string",
          "index":"not_analyzed"
        },
        "EXT_COL1":{
          "type":"string",
          "index":"not_analyzed"
        },
        "EXT_COL2":{
          "type":"string",
          "index":"not_analyzed"
        },
        "EXT_COL3":{
          "type":"string",
          "index":"not_analyzed"
        },
        "EXT_COL4":{
          "type":"string",
          "index":"not_analyzed"
        },
        "EXT_COL5":{
          "type":"string",
          "index":"not_analyzed"
        },
        "EXT_COL6":{
          "type":"string",
          "index":"not_analyzed"
        },
        "EXT_COL7":{
          "type":"string",
          "index":"not_analyzed"
        },
        "EXT_COL8":{
          "type":"string",
          "index":"not_analyzed"
        },
        "EXT_COL9":{
          "type":"string",
          "index":"not_analyzed"
        },
        "EXT_COL10":{
          "type":"string",
          "index":"not_analyzed"
        }

      }
    },
    "item_agg": {
      "properties": {
        "ITEM_ID": {
          "type": "string",
          "index": "not_analyzed"
        },
        "CATEGORY_ID": {
          "type": "string",
          "index": "not_analyzed"
        },
        "SPU_ID": {
          "type": "string",
          "index": "not_analyzed"
        },
        "ITEM_TYPE": {
          "type": "string",
          "index": "not_analyzed"
        },
        "SPEC_HEAD_ID":{
          "type":"string",
          "index": "not_analyzed"
        },
        "ITEM_CODE": {
          "type": "string",
          "index": "not_analyzed"
        },
        "ITEM_NAME": {
          "type": "multi_field",
          "fields": {
            "pinyin": {
              "type": "string",
              "store": "no",
              "term_vector": "with_positions_offsets",
              "analyzer": "pinyin_analyzer",
              "boost": 10
            },
            "ITEM_NAME": {
              "type": "string",
              "term_vector": "with_positions_offsets",
              "index": "analyzed",
              "analyzer": "optimizeIK",
              "search_analyzer": "optimizeIK",
              "include_in_all": "true"
            }
          }
        },
        "ITEM_SHORTNAME": {
          "type": "string",
          "term_vector": "with_positions_offsets",
          "index": "analyzed",
          "analyzer": "optimizeIK",
          "search_analyzer": "optimizeIK",
          "include_in_all": "true"
        },
        "ITEM_STATUS": {
          "type": "string",
          "index": "not_analyzed"
        },
        "ITEM_DESC": {
          "type": "string",
          "term_vector": "with_positions_offsets",
          "index": "analyzed",
          "analyzer": "optimizeIK",
          "search_analyzer": "optimizeIK",
          "include_in_all": "true"
        },
        "TRADEMARK": {
          "type": "string",
          "index": "not_analyzed"
        },
        "PRIMARY_UNIT_CODE":{
          "type":"string",
          "index": "not_analyzed"
        },
        "VALID_START":{
          "type": "date",
          "format": "yyyy-MM-dd HH:mm:ss||yyyy-MM-dd||epoch_millis"
        },
        "VALID_END":{
          "type": "date",
          "format": "yyyy-MM-dd HH:mm:ss||yyyy-MM-dd||epoch_millis"
        },
        "EFFECT_USER_ID":{
          "type":"string",
          "index": "not_analyzed"
        },
        "EFFECT_DATE":{
          "type": "date",
          "format": "yyyy-MM-dd HH:mm:ss||yyyy-MM-dd||epoch_millis"
        },
        "INVALID_USER_ID":{
          "type":"string",
          "index": "not_analyzed"
        },
        "INVALID_DATE":{
          "type": "date",
          "format": "yyyy-MM-dd HH:mm:ss||yyyy-MM-dd||epoch_millis"
        },
        "SECONDARY_UNIT_CODE":{
          "type":"string",
          "index": "not_analyzed"
        },
        "PO_MOREORLESS_UP":{
          "type":"double"
        },
        "PO_MOREORLESS_DOWN":{
          "type":"double"
        },
        "ONT_MOREORLESS_UP":{
          "type":"double"
        },
        "ONT_MOREORLESS_DOWN":{
          "type":"double"
        },
        "UOM_WIDTH":{
          "type":"string",
          "index": "not_analyzed"
        },
        "UOM_HEIGHT":{
          "type":"string",
          "index": "not_analyzed"
        },
        "UOM_LENGTH":{
          "type":"string",
          "index": "not_analyzed"
        },
        "UOM_DENSITY":{
          "type":"string",
          "index": "not_analyzed"
        },
        "UOM_WEIGHT":{
          "type":"string",
          "index": "not_analyzed"
        },
        "HS_CODE":{
          "type":"string",
          "index": "not_analyzed"
        },
        "MARK_CODE":{
          "type":"string",
          "index": "not_analyzed"
        },
        "MANUFACTURER_NAME":{
          "type":"string",
          "index": "not_analyzed"
        },
        "TECHNICAL_STANDARD":{
          "type":"string",
          "index": "not_analyzed"
        },
        "GOLDEN_TAX_CODE":{
          "type":"string",
          "index": "not_analyzed"
        },
        "LOSS_RATE":{
          "type":"double"
        },
        "STANDARD_FLAG":{
          "type":"string",
          "index": "not_analyzed"
        },
        "ORIGIN":{
          "type":"string",
          "index": "not_analyzed"
        },
        "LOCK_FLAG":{
          "type":"string",
          "index": "not_analyzed"
        },
        "SPEC_VALUE1": {
          "type": "string",
          "index": "not_analyzed"
        },
        "SPEC_VALUE2": {
          "type": "string",
          "index": "not_analyzed"
        },
        "SPEC_VALUE3": {
          "type": "string",
          "index": "not_analyzed"
        },
        "SPEC_VALUE4": {
          "type": "string",
          "index": "not_analyzed"
        },
        "SPEC_VALUE5": {
          "type": "string",
          "index": "not_analyzed"
        },
        "SPEC_VALUE6": {
          "type": "string",
          "index": "not_analyzed"
        },
        "SPEC_VALUE7": {
          "type": "string",
          "index": "not_analyzed"
        },
        "SPEC_VALUE8": {
          "type": "string",
          "index": "not_analyzed"
        },
        "SPEC_VALUE9": {
          "type": "string",
          "index": "not_analyzed"
        },
        "SPEC_VALUE10": {
          "type": "string",
          "index": "not_analyzed"
        },
        "SPEC_VALUE11": {
          "type": "string",
          "index": "not_analyzed"
        },
        "SPEC_VALUE12": {
          "type": "string",
          "index": "not_analyzed"
        },
        "SPEC_VALUE13": {
          "type": "string",
          "index": "not_analyzed"
        },
        "SPEC_VALUE14": {
          "type": "string",
          "index": "not_analyzed"
        },
        "SPEC_VALUE15": {
          "type": "string",
          "index": "not_analyzed"
        },
        "SPEC_VALUE16": {
          "type": "string",
          "index": "not_analyzed"
        },
        "SPEC_VALUE17": {
          "type": "string",
          "index": "not_analyzed"
        },
        "SPEC_VALUE18": {
          "type": "string",
          "index": "not_analyzed"
        },
        "SPEC_VALUE19": {
          "type": "string",
          "index": "not_analyzed"
        },
        "SPEC_VALUE20": {
          "type": "string",
          "index": "not_analyzed"
        },
        "CREATE_USER_ID": {
          "type": "string",
          "index": "not_analyzed"
        },
        "CREATE_DATE": {
          "type": "date",
          "format": "yyyy-MM-dd HH:mm:ss||yyyy-MM-dd||epoch_millis"
        },
        "CREATE_USER_NAME": {
          "type": "string",
          "index": "not_analyzed"
        },
        "MODIFY_USER_ID": {
          "type": "string",
          "index": "not_analyzed"
        },
        "MODIFY_USER_NAME": {
          "type": "string",
          "index": "not_analyzed"
        },
        "MODIFY_DATE": {
          "type": "date",
          "format": "yyyy-MM-dd HH:mm:ss||yyyy-MM-dd||epoch_millis"
        },
        "ORG_ID": {
          "type": "string",
          "index": "not_analyzed"
        },
        "GROUP_ID": {
          "type": "string",
          "index": "not_analyzed"
        },
        "BOOK_ID": {
          "type": "string",
          "index": "not_analyzed"
        },
        "EXT_COL1": {
          "type": "string",
          "index": "not_analyzed"
        },
        "EXT_COL2": {
          "type": "string",
          "index": "not_analyzed"
        },
        "EXT_COL3": {
          "type": "string",
          "index": "not_analyzed"
        },
        "EXT_COL4": {
          "type": "string",
          "index": "not_analyzed"
        },
        "EXT_COL5": {
          "type": "string",
          "index": "not_analyzed"
        },
        "EXT_COL6": {
          "type": "string",
          "index": "not_analyzed"
        },
        "EXT_COL7": {
          "type": "string",
          "index": "not_analyzed"
        },
        "EXT_COL8": {
          "type": "string",
          "index": "not_analyzed"
        },
        "EXT_COL9": {
          "type": "string",
          "index": "not_analyzed"
        },
        "EXT_COL10": {
          "type": "string",
          "index": "not_analyzed"
        },
        "FROM_TYPE":{
          "type":"string",
          "index": "not_analyzed"
        },
        "FROM_ID":{
          "type":"string",
          "index": "not_analyzed"
        },
        "TAX_CODE_TYPE":{
          "type":"string",
          "index": "not_analyzed"
        },
        "TAX_RATE":{
          "type":"string",
          "index": "not_analyzed"
        },
        "ITEM_DETAIL_NOTES": {
          "type": "string",
          "term_vector": "with_positions_offsets",
          "index": "analyzed",
          "analyzer": "optimizeIK",
          "search_analyzer": "optimizeIK",
          "include_in_all": "true"
        },
        "cmc_brand": {
          "properties": {
            "BRAND_ID": {
              "type": "string",
              "index": "not_analyzed"
            },
            "BRAND_NAME": {
              "type": "multi_field",
              "fields": {
                "pinyin": {
                  "type": "string",
                  "store": "no",
                  "term_vector": "with_positions_offsets",
                  "analyzer": "pinyin_analyzer",
                  "boost": 10
                },
                "BRAND_NAME": {
                  "type": "string",
                  "term_vector": "with_positions_offsets",
                  "index": "analyzed",
                  "analyzer": "optimizeIK",
                  "search_analyzer": "optimizeIK",
                  "include_in_all": "true"
                }
              }
            },
            "STATUS": {
              "type": "string",
              "index": "not_analyzed"
            },
            "BRIEF_NAME": {
              "type": "multi_field",
              "fields": {
                "pinyin": {
                  "type": "string",
                  "store": "no",
                  "term_vector": "with_positions_offsets",
                  "analyzer": "pinyin_analyzer",
                  "boost": 10
                },
                "BRIEF_NAME": {
                  "type": "string",
                  "term_vector": "with_positions_offsets",
                  "index": "analyzed",
                  "analyzer": "optimizeIK",
                  "search_analyzer": "optimizeIK",
                  "include_in_all": "true"
                }
              }
            },
            "WEBSITE": {
              "type": "string",
              "index": "not_analyzed"
            },
            "CATEGORY_ID": {
              "type": "string",
              "index": "not_analyzed"
            },
            "LOGO_URL":{
              "type":"string",
              "index": "not_analyzed"
            },

            "BRAND_STORY_TITLE":{
              "type":"string",
              "index": "not_analyzed"
            },
            "BELONG_COUNTRY": {
              "type": "string",
              "index": "not_analyzed"
            },
            "BELONG_COMPANY":{
              "type":"string",
              "index": "not_analyzed"
            },
            "FOUND_YEAR":{
              "type":"string",
              "index": "not_analyzed"
            },

            "CREATE_USER_ID":{
              "type":"string",
              "index": "not_analyzed"
            },
            "CREATE_DATE":{
              "type": "date",
              "format": "yyyy-MM-dd HH:mm:ss||yyyy-MM-dd||epoch_millis"
            },

            "MODIFY_USER_ID":{
              "type":"string",
              "index": "not_analyzed"
            },
            "MODIFY_DATE":{
              "type": "date",
              "format": "yyyy-MM-dd HH:mm:ss||yyyy-MM-dd||epoch_millis"
            },
            "ORG_ID": {
              "type": "string",
              "index": "not_analyzed"
            },
            "BOOK_ID": {
              "type": "string",
              "index": "not_analyzed"
            },
            "GROUP_ID": {
              "type": "string",
              "index": "not_analyzed"
            },

            "EXT_COL1": {
              "type": "string",
              "index": "not_analyzed"
            },
            "EXT_COL2": {
              "type": "string",
              "index": "not_analyzed"
            },
            "EXT_COL3": {
              "type": "string",
              "index": "not_analyzed"
            },
            "EXT_COL4": {
              "type": "string",
              "index": "not_analyzed"
            },
            "EXT_COL5": {
              "type": "string",
              "index": "not_analyzed"
            },
            "EXT_COL6": {
              "type": "string",
              "index": "not_analyzed"
            },
            "EXT_COL7": {
              "type": "string",
              "index": "not_analyzed"
            },
            "EXT_COL8": {
              "type": "string",
              "index": "not_analyzed"
            },
            "EXT_COL9": {
              "type": "string",
              "index": "not_analyzed"
            },
            "EXT_COL10": {
              "type": "string",
              "index": "not_analyzed"
            },
            "CREATE_USER_NAME":{
              "type":"string",
              "index": "not_analyzed"
            },
            "MODIFY_USER_NAME":{
              "type":"string",
              "index": "not_analyzed"
            },
            "BRAND_INTRODUCTION_NOTES":{
              "type":"string",
              "index": "not_analyzed"
            },
            "BRAND_STORY_NOTES":{
              "type": "string",
              "term_vector": "with_positions_offsets",
              "index": "analyzed",
              "analyzer": "optimizeIK",
              "search_analyzer": "optimizeIK",
              "include_in_all": "true"
            }
          }
        },
        "SPEC_CONTENTS": {
          "type":"nested",
          "properties": {
            "PRICE_FLAG": {
              "type": "string",
              "index": "not_analyzed"
            },
            "ATTRIBUTE_NAME": {
              "type": "string",
              "index": "not_analyzed"
            },
            "ATTRIBUTE_VALUE": {
              "type": "string",
              "index": "not_analyzed"
            }
          }
        },
        "cmc_category": {
          "properties": {
            "CATEGORY_CODE": {
              "type": "string",
              "index": "not_analyzed"
            },
            "CATEGORY_ID": {
              "type": "string",
              "index": "not_analyzed"
            },
            "CATEGORY_LEVEL": {
              "type": "string",
              "index": "not_analyzed"
            },
            "CATEGORY_NAME": {
              "type": "string",
              "term_vector": "with_positions_offsets",
              "index": "analyzed",
              "analyzer": "optimizeIK",
              "search_analyzer": "optimizeIK",
              "include_in_all": "true"
            }
          }
        },
        "aus_at_picture_list": {
          "properties": {
            "PICTURE_ID": {
              "type": "string",
              "index": "not_analyzed"
            },
            "BILL_NO": {
              "type": "string",
              "index": "not_analyzed"
            },
            "BILL_TYPE": {
              "type": "string",
              "index": "not_analyzed"
            },
            "PIC_NAME": {
              "type": "string",
              "index": "not_analyzed"
            },
            "PIC_TYPE": {
              "type": "string",
              "index": "not_analyzed"
            },
            "FILE_PATH": {
              "type": "string",
              "index": "not_analyzed"
            },
            "PIC_SIZE": {
              "type": "double"
            },
            "PIC_STORAGE_NAME":{
              "type": "string",
              "index": "not_analyzed"
            },

            "PIC_EX_FILEID":{
              "type": "string",
              "index": "not_analyzed"
            },
            "SMALL_SIZE_NAME":{
              "type": "string",
              "index": "not_analyzed"
            },
            "SMALL_SIZE_EX_FILE_ID":{
              "type": "string",
              "index": "not_analyzed"
            },
            "MIDDLE_SIZE_NAME":{
              "type": "string",
              "index": "not_analyzed"
            },
            "MIDDLE_SIZE_EX_FILE_ID":{
              "type": "string",
              "index": "not_analyzed"
            },

            "PIC_STATUS":{
              "type": "string",
              "index": "not_analyzed"
            },

            "CREATE_DATE": {
              "type": "date",
              "format": "yyyy-MM-dd HH:mm:ss||yyyy-MM-dd||epoch_millis"
            },
            "CREATE_USER_ID": {
              "type": "string",
              "index": "not_analyzed"
            },
            "CREATE_USER_NAME": {
              "type": "string",
              "index": "not_analyzed"
            },

            "BOOK_ID": {
              "type": "string",
              "index": "not_analyzed"
            },

            "GROUP_ID": {
              "type": "string",
              "index": "not_analyzed"
            },
            "ORG_ID": {
              "type": "string",
              "index": "not_analyzed"
            },

            "MODIFY_DATE": {
              "type": "date",
              "format": "yyyy-MM-dd HH:mm:ss||yyyy-MM-dd||epoch_millis"
            },
            "MODIFY_USER_ID": {
              "type": "string",
              "index": "not_analyzed"
            },
            "MODIFY_USER_NAME": {
              "type": "string",
              "index": "not_analyzed"
            },
            "EXT_COL1": {
              "type": "string",
              "index": "not_analyzed"
            },
            "EXT_COL2": {
              "type": "string",
              "index": "not_analyzed"
            },
            "EXT_COL3": {
              "type": "string",
              "index": "not_analyzed"
            },
            "EXT_COL4": {
              "type": "string",
              "index": "not_analyzed"
            },
            "EXT_COL5": {
              "type": "string",
              "index": "not_analyzed"
            },
            "EXT_COL6": {
              "type": "string",
              "index": "not_analyzed"
            },
            "EXT_COL7": {
              "type": "string",
              "index": "not_analyzed"
            },
            "EXT_COL8": {
              "type": "string",
              "index": "not_analyzed"
            },
            "EXT_COL9": {
              "type": "string",
              "index": "not_analyzed"
            },
            "EXT_COL10": {
              "type": "string",
              "index": "not_analyzed"
            },
            "EXT_COL11": {
              "type": "string",
              "index": "not_analyzed"
            },
            "EXT_COL12": {
              "type": "string",
              "index": "not_analyzed"
            },
            "EXT_COL13": {
              "type": "string",
              "index": "not_analyzed"
            },
            "EXT_COL14": {
              "type": "string",
              "index": "not_analyzed"
            },
            "EXT_COL15": {
              "type": "string",
              "index": "not_analyzed"
            },
            "EXT_COL16": {
              "type": "string",
              "index": "not_analyzed"
            },
            "EXT_COL17": {
              "type": "string",
              "index": "not_analyzed"
            },
            "EXT_COL18": {
              "type": "string",
              "index": "not_analyzed"
            },
            "EXT_COL19": {
              "type": "string",
              "index": "not_analyzed"
            },
            "EXT_COL20": {
              "type": "string",
              "index": "not_analyzed"
            }
          }
        },
        "cmc_spu": {
          "properties": {
            "SPU_ID": {
              "type": "string",
              "index": "not_analyzed"
            },
            "CATEGORY_ID": {
              "type": "string",
              "index": "not_analyzed"
            },
            "SPEC_HEAD_ID": {
              "type": "string",
              "index": "not_analyzed"
            },
            "SPU_CODE": {
              "type": "string",
              "index": "not_analyzed"
            },
            "SPU_NAME": {
              "type": "multi_field",
              "fields": {
                "pinyin": {
                  "type": "string",
                  "store": "no",
                  "term_vector": "with_positions_offsets",
                  "analyzer": "pinyin_analyzer",
                  "boost": 10
                },
                "SPU_NAME": {
                  "type": "string",
                  "term_vector": "with_positions_offsets",
                  "index": "analyzed",
                  "analyzer": "optimizeIK",
                  "search_analyzer": "optimizeIK",
                  "include_in_all": "true"
                }
              }
            },
            "SPU_STATUS": {
              "type": "string",
              "index": "not_analyzed"
            },
            "SPU_TYPE": {
              "type": "string",
              "index": "not_analyzed"
            },
            "SPU_DESC": {
              "type": "string",
              "term_vector": "with_positions_offsets",
              "index": "analyzed",
              "analyzer": "optimizeIK",
              "search_analyzer": "optimizeIK",
              "include_in_all": "true"
            },

            "SPU_DETAIL":{
              "type": "string",
              "term_vector": "with_positions_offsets",
              "index": "analyzed",
              "analyzer": "optimizeIK",
              "search_analyzer": "optimizeIK",
              "include_in_all": "true"
            },
            "BRAND":{
              "type":"string",
              "index": "not_analyzed"
            },

            "PRIMARY_UNIT_CODE":{
              "type":"string",
              "index": "not_analyzed"
            },

            "TAX_RATE": {
              "type": "string",
              "index": "not_analyzed"
            },
            "SPEC_VALUE1": {
              "type": "string",
              "index": "not_analyzed"
            },
            "SPEC_VALUE2": {
              "type": "string",
              "index": "not_analyzed"
            },
            "SPEC_VALUE3": {
              "type": "string",
              "index": "not_analyzed"
            },
            "SPEC_VALUE4": {
              "type": "string",
              "index": "not_analyzed"
            },
            "SPEC_VALUE5": {
              "type": "string",
              "index": "not_analyzed"
            },
            "SPEC_VALUE6": {
              "type": "string",
              "index": "not_analyzed"
            },
            "SPEC_VALUE7": {
              "type": "string",
              "index": "not_analyzed"
            },
            "SPEC_VALUE8": {
              "type": "string",
              "index": "not_analyzed"
            },

            "SPEC_VALUE9": {
              "type": "string",
              "index": "not_analyzed"
            },
            "SPEC_VALUE10": {
              "type": "string",
              "index": "not_analyzed"
            },
            "SPEC_VALUE11": {
              "type": "string",
              "index": "not_analyzed"
            },
            "SPEC_VALUE12": {
              "type": "string",
              "index": "not_analyzed"
            },
            "SPEC_VALUE13": {
              "type": "string",
              "index": "not_analyzed"
            },
            "SPEC_VALUE14": {
              "type": "string",
              "index": "not_analyzed"
            },
            "SPEC_VALUE15": {
              "type": "string",
              "index": "not_analyzed"
            },
            "SPEC_VALUE16": {
              "type": "string",
              "index": "not_analyzed"
            },
            "SPEC_VALUE17": {
              "type": "string",
              "index": "not_analyzed"
            },
            "SPEC_VALUE18": {
              "type": "string",
              "index": "not_analyzed"
            },
            "SPEC_VALUE19": {
              "type": "string",
              "index": "not_analyzed"
            },
            "SPEC_VALUE20": {
              "type": "string",
              "index": "not_analyzed"
            },
            "CREATE_USER_ID":{
              "type":"string",
              "index": "not_analyzed"
            },
            "CREATE_DATE":{
              "type": "date",
              "format": "yyyy-MM-dd HH:mm:ss||yyyy-MM-dd||epoch_millis"
            },

            "MODIFY_USER_ID":{
              "type":"string",
              "index": "not_analyzed"
            },
            "MODIFY_DATE":{
              "type": "date",
              "format": "yyyy-MM-dd HH:mm:ss||yyyy-MM-dd||epoch_millis"
            },
            "ORG_ID": {
              "type": "string",
              "index": "not_analyzed"
            },
            "BOOK_ID": {
              "type": "string",
              "index": "not_analyzed"
            },

            "GROUP_ID": {
              "type": "string",
              "index": "not_analyzed"
            },
            "EXT_COL1": {
              "type": "string",
              "index": "not_analyzed"
            },
            "EXT_COL2": {
              "type": "string",
              "index": "not_analyzed"
            },
            "EXT_COL3": {
              "type": "string",
              "index": "not_analyzed"
            },
            "EXT_COL4": {
              "type": "string",
              "index": "not_analyzed"
            },
            "EXT_COL5": {
              "type": "string",
              "index": "not_analyzed"
            },
            "EXT_COL6": {
              "type": "string",
              "index": "not_analyzed"
            },
            "EXT_COL7": {
              "type": "string",
              "index": "not_analyzed"
            },
            "EXT_COL8": {
              "type": "string",
              "index": "not_analyzed"
            },
            "EXT_COL9": {
              "type": "string",
              "index": "not_analyzed"
            },
            "EXT_COL10": {
              "type": "string",
              "index": "not_analyzed"
            },
            "CREATE_USER_NAME":{
              "type":"string",
              "index": "not_analyzed"
            },
            "MODIFY_USER_NAME":{
              "type":"string",
              "index": "not_analyzed"
            },
            "TAX_CODE_TYPE":{
              "type":"string",
              "index": "not_analyzed"
            },
            "SPU_DETAIL_NOTES":{
              "type": "string",
              "term_vector": "with_positions_offsets",
              "index": "analyzed",
              "analyzer": "optimizeIK",
              "search_analyzer": "optimizeIK",
              "include_in_all": "true"
            }
          }
        }
      }
    }
  }
}




